prefect_tool_state/__init__.py
prefect_tool_state/tool_state.py
prefect_tool_state/tool_state_manager.py
prefect_tool_state/tool_state_publisher.py
prefect_tool_state-0.0.8.dist-info/licenses/LICENSE
prefect_tool_state-0.0.8.dist-info/METADATA
prefect_tool_state-0.0.8.dist-info/WHEEL
prefect_tool_state-0.0.8.dist-info/top_level.txt
prefect_tool_state-0.0.8.dist-info/RECORD
