Metadata-Version: 2.4
Name: prefect-tool-state
Version: 0.0.8
Summary: A high-throughput progress publisher for Prefect tools with optimized batching
Author-email: Team <team@example.com>
Project-URL: Homepage, https://github.com/your-org/prefect-tool-state
Project-URL: Bug Tracker, https://github.com/your-org/prefect-tool-state/issues
Project-URL: Documentation, https://github.com/your-org/prefect-tool-state#readme
Classifier: Programming Language :: Python :: 3
Classifier: License :: OSI Approved :: MIT License
Classifier: Operating System :: OS Independent
Classifier: Development Status :: 3 - Alpha
Classifier: Intended Audience :: Developers
Classifier: Topic :: Software Development :: Libraries :: Python Modules
Requires-Python: >=3.8
License-File: LICENSE
Dynamic: license-file
